setup.py
tyoi/__init__.py
tyoi.OAuth2.egg-info/PKG-INFO
tyoi.OAuth2.egg-info/SOURCES.txt
tyoi.OAuth2.egg-info/dependency_links.txt
tyoi.OAuth2.egg-info/top_level.txt
tyoi/oauth2/__init__.py
tyoi/oauth2/authenticators/__init__.py
tyoi/oauth2/grants/__init__.py