Metadata-Version: 1.0
Name: tyoi.OAuth2
Version: 0.2.1
Summary: Implements the client side of the OAuth 2 protocol
Home-page: https://github.com/ryanhorn/tyoiOAuth2
Author: Ryan Horn
Author-email: ryan.horn.web@gmail.com
License: UNKNOWN
Keywords: oauth oauth2 auth authentication
Platform: UNKNOWN
